{
  "timestamp": "2025-12-06T11:43:55.742101",
  "mode": "synthetic_example",
  "match": {
    "duration_s": 180,
    "elapsed_s": 67.3,
    "time_remaining_s": 112.7,
    "status": "in_progress"
  },
  "robots": {
    "robot_4": {
      "name": "AI Robot",
      "pose": {
        "x_m": 1.23,
        "y_m": 0.87,
        "theta_rad": 1.57
      },
      "velocity": {
        "vx_m_s": 0.03,
        "vy_m_s": -0.01,
        "omega_rad_s": 0.02
      },
      "hits_received": 2,
      "hits_inflicted": 3,
      "last_shot_time": 61.2
    },
    "robot_5": {
      "name": "Human Robot",
      "pose": {
        "x_m": 1.85,
        "y_m": 1.42,
        "theta_rad": -0.52
      },
      "velocity": {
        "vx_m_s": -0.08,
        "vy_m_s": 0.05,
        "omega_rad_s": -0.1
      },
      "hits_received": 3,
      "hits_inflicted": 2,
      "last_shot_time": 58.7
    }
  },
  "ai_state": {
    "current_behavior": "ATTACK",
    "target_position": [
      1.85,
      1.42
    ],
    "path_waypoints_count": 12,
    "has_line_of_sight": true,
    "fire_request": true,
    "safe_distance_m": 0.8
  },
  "cooldowns": {
    "human_next_shot": 72.7,
    "ai_next_shot": 64.2
  }
}